babelfont/Anchor.py
babelfont/Axis.py
babelfont/BaseObject.py
babelfont/Component.py
babelfont/Features.py
babelfont/Font.py
babelfont/Glyph.py
babelfont/Guide.py
babelfont/Instance.py
babelfont/Layer.py
babelfont/Master.py
babelfont/Names.py
babelfont/Node.py
babelfont/Shape.py
babelfont/__init__.py
babelfont/__main__.py
babelfont/convertors/__init__.py
babelfont/convertors/designspace.py
babelfont/convertors/fontforge.py
babelfont/convertors/gsobject.py
babelfont/convertors/nfsf.py
babelfont/convertors/truetype.py
babelfont/convertors/ufo.py
babelfont/convertors/fontlab/__init__.py
babelfont/convertors/fontlab/vfb.py
babelfont/convertors/fontlab/vfj.py
babelfont/convertors/glyphs/__init__.py
babelfont/convertors/glyphs/glyphs2.py
babelfont/convertors/glyphs/glyphs3.py
babelfont/convertors/glyphs/glyphspackage.py
babelfont/convertors/glyphs/utils.py
babelfont/data/GlyphData.xml
babelfont/data/__init__.py
babelfont/fontFilters/__init__.py
babelfont/fontFilters/anchorPropagation.py
babelfont/fontFilters/background.py
babelfont/fontFilters/cu2qu.py
babelfont/fontFilters/customParameters.py
babelfont/fontFilters/decomposeMixed.py
babelfont/fontFilters/dropUnexported.py
babelfont/fontFilters/featureWriters.py
babelfont/fontFilters/fillOpentype.py
babelfont/fontFilters/glyphDataXML.py
babelfont/fontFilters/glyphs3fea.py
babelfont/fontFilters/intermediateLayer.py
babelfont/fontFilters/marks.py
babelfont/fontFilters/rename.py
babelfont-3.1.0.dist-info/AUTHORS.txt
babelfont-3.1.0.dist-info/LICENSE
babelfont-3.1.0.dist-info/METADATA
babelfont-3.1.0.dist-info/WHEEL
babelfont-3.1.0.dist-info/entry_points.txt
babelfont-3.1.0.dist-info/top_level.txt
babelfont-3.1.0.dist-info/RECORD
