Metadata-Version: 2.1
Name: babelfont
Version: 3.1.0
Summary: Load, examine and save fonts in a variety of formats
Author-email: Simon Cozens <simon@simon-cozens.org>
License-File: LICENSE
License-File: AUTHORS.txt
Requires-Dist: orjson >=3.5.1
Requires-Dist: fonttools >=4.53.1
Requires-Dist: ufoLib2 >=0.16.0
Requires-Dist: openstep-plist >=0.2.2
Requires-Dist: ufomerge >=1.8.0
Provides-Extra: dev
Requires-Dist: pytest ; extra == 'dev'
Requires-Dist: defcon ; extra == 'dev'
Provides-Extra: read-ttf
Requires-Dist: fontfeatures >=1.8.0 ; extra == 'read-ttf'
Provides-Extra: vfb
Requires-Dist: vfbLib >=0.7.1 ; extra == 'vfb'
